Metadata-Version: 1.1
Name: speechpy-fast
Version: 2.4
Summary: A fork of the python package for extracting speech features.
Home-page: https://github.com/matthewscholefield/speechpy
Author: Amirsina Torfi, Matthew Scholefield
Author-email: matthew331199@gmail.com
License: UNKNOWN
Download-URL: https://github.com/matthewscholefield/speechpy/archive/2.4.zip
Platform: UNKNOWN
